captureflow/__init__.py
captureflow/config.py
captureflow/distro.py
captureflow/instrumentation.py
captureflow/resource.py
captureflow/span_processor.py
captureflow/tracer_provider.py
captureflow_agent-0.0.16.dist-info/entry_points.txt
captureflow_agent-0.0.16.dist-info/WHEEL
captureflow_agent-0.0.16.dist-info/METADATA
captureflow_agent-0.0.16.dist-info/RECORD
